odoo10_addon_base_technical_features-10.0.1.0.0-py2.7-nspkg.pth
odoo10_addon_base_technical_features-10.0.1.0.0.dist-info/top_level.txt
odoo10_addon_base_technical_features-10.0.1.0.0.dist-info/WHEEL
odoo10_addon_base_technical_features-10.0.1.0.0.dist-info/RECORD
odoo10_addon_base_technical_features-10.0.1.0.0.dist-info/metadata.json
odoo10_addon_base_technical_features-10.0.1.0.0.dist-info/DESCRIPTION.rst
odoo10_addon_base_technical_features-10.0.1.0.0.dist-info/METADATA
odoo10_addon_base_technical_features-10.0.1.0.0.dist-info/namespace_packages.txt
odoo/addons/base_technical_features/__manifest__.py
odoo/addons/base_technical_features/__init__.py
odoo/addons/base_technical_features/README.rst
odoo/addons/base_technical_features/security/res_groups.xml
odoo/addons/base_technical_features/models/ir_ui_menu.py
odoo/addons/base_technical_features/models/__init__.py
odoo/addons/base_technical_features/models/base.py
odoo/addons/base_technical_features/models/res_users.py
odoo/addons/base_technical_features/i18n/zh_CN.po
odoo/addons/base_technical_features/i18n/pt.po
odoo/addons/base_technical_features/i18n/it.po
odoo/addons/base_technical_features/i18n/es.po
odoo/addons/base_technical_features/i18n/tr.po
odoo/addons/base_technical_features/i18n/hr.po
odoo/addons/base_technical_features/i18n/gl.po
odoo/addons/base_technical_features/i18n/ca.po
odoo/addons/base_technical_features/i18n/sl.po
odoo/addons/base_technical_features/i18n/es_ES.po
odoo/addons/base_technical_features/i18n/pt_PT.po
odoo/addons/base_technical_features/i18n/nl.po
odoo/addons/base_technical_features/i18n/am.po
odoo/addons/base_technical_features/i18n/de.po
odoo/addons/base_technical_features/i18n/fr.po
odoo/addons/base_technical_features/i18n/pt_BR.po
odoo/addons/base_technical_features/i18n/el_GR.po
odoo/addons/base_technical_features/i18n/fi.po
odoo/addons/base_technical_features/i18n/hr_HR.po
odoo/addons/base_technical_features/views/res_users.xml
odoo/addons/base_technical_features/data/res_users.xml
odoo/addons/base_technical_features/tests/test_base_technical_features.py
odoo/addons/base_technical_features/tests/__init__.py
odoo/addons/base_technical_features/static/description/user_preferences.png
odoo/addons/base_technical_features/static/description/icon.png
